wallabaggins/__init__.py
wallabaggins/__main__.py
wallabaggins/api.py
wallabaggins/cli.py
wallabaggins/conf.py
wallabaggins/entry.py
wallabaggins/wallabag_list.py
wallabaggins/wallabag_show.py
wallabaggins-0.0.12.dist-info/licenses/LICENSE
wallabaggins-0.0.12.dist-info/METADATA
wallabaggins-0.0.12.dist-info/WHEEL
wallabaggins-0.0.12.dist-info/entry_points.txt
wallabaggins-0.0.12.dist-info/top_level.txt
wallabaggins-0.0.12.dist-info/RECORD
