Metadata-Version: 2.4
Name: wallabaggins
Version: 0.0.12
Summary: A wallabag CLI client
Author-email: David Breese <dabreese00@gmail.com>
License-Expression: MIT
Project-URL: Homepage, https://codeberg.org/dabreese00/wallabaggins
Classifier: Programming Language :: Python :: 3
Classifier: Operating System :: POSIX :: Linux
Requires-Python: >=3.14
License-File: LICENSE
Requires-Dist: beautifulsoup4>=4.5.1
Requires-Dist: requests>=2.11.1
Requires-Dist: secretstorage>=3.5.0
Dynamic: license-file
